flask_sub_apps/__init__.py
flask_sub_apps/config.py
flask_sub_apps/helpers.py
flask_sub_apps/loader.py
flask_sub_apps/models.py
flask_sub_apps/registry.py
flask_sub_apps/type_validation.py
flask_sub_apps-0.1.4.dist-info/METADATA
flask_sub_apps-0.1.4.dist-info/WHEEL
flask_sub_apps-0.1.4.dist-info/top_level.txt
flask_sub_apps-0.1.4.dist-info/RECORD
