Metadata-Version: 2.1
Name: flask-sub-apps
Version: 0.1.4
Summary: Flask package for auto-loading sub-apps
Author: Damian Ciftci
License: MIT
Platform: UNKNOWN
Classifier: Programming Language :: Python
Classifier: Framework :: Flask
Classifier: License :: OSI Approved :: MIT License
Classifier: Operating System :: OS Independent
Classifier: Intended Audience :: Developers
Classifier: Topic :: Software Development :: Libraries :: Python Modules
Requires-Dist: flask
Requires-Dist: flask-sqlalchemy
Requires-Dist: click
Requires-Dist: python-module-loader
